Metadata-Version: 2.1
Name: sqlite-utils-sqlite-jsonschema
Version: 0.2.3
Summary: TODO
Author: Alex Garcia
License: Apache-2.0
Project-URL: Homepage, https://github.com/asg017/sqlite-jsonschema
Project-URL: Changelog, https://github.com/asg017/sqlite-jsonschema/releases
Project-URL: Issues, https://github.com/asg017/sqlite-jsonschema/issues
Requires-Dist: sqlite-utils
Requires-Dist: sqlite-jsonschema
